README.rst
docoptcfg.py
setup.py
docoptcfg.egg-info/PKG-INFO
docoptcfg.egg-info/SOURCES.txt
docoptcfg.egg-info/dependency_links.txt
docoptcfg.egg-info/requires.txt
docoptcfg.egg-info/top_level.txt
docoptcfg.egg-info/zip-safe